typestring_parser/__init__.py
typestring_parser/errors.py
typestring_parser/parser.py
typestring_parser-0.1.dist-info/LICENSE.rst
typestring_parser-0.1.dist-info/WHEEL
typestring_parser-0.1.dist-info/METADATA
typestring_parser-0.1.dist-info/RECORD
