Metadata-Version: 2.1
Name: typestring-parser
Version: 0.1
Summary: Parse type strings into typing instances
Home-page: https://github.com/Dominik1123/typestring-parser
License: MIT
Author: Dominik1123
Requires-Python: >=3.7.9,<4.0.0
Classifier: License :: OSI Approved :: MIT License
Classifier: Programming Language :: Python :: 3
Classifier: Programming Language :: Python :: 3.7
Classifier: Programming Language :: Python :: 3.8
Classifier: Programming Language :: Python :: 3.9
Requires-Dist: importlib_metadata (>=1.6.1,<2.0.0); python_version < "3.8"
Requires-Dist: pyparsing (>=2.4.7,<3.0.0)
Requires-Dist: typing-extensions (>=3.7.4.3,<4.0.0.0); python_version < "3.9"
Project-URL: Changelog, https://github.com/Dominik1123/typestring-parser/releases
Project-URL: Repository, https://github.com/Dominik1123/typestring-parser
